LICENSE
README.rst
pyproject.toml
setup.py
network_changer/__init__.py
network_changer/async_helpers.py
network_changer/errors.py
network_changer/executor.py
network_changer/info.py
network_changer/interface.py
network_changer/progress.py
network_changer/retrier.py
network_changer/shell.py
network_changer/version.py
network_changer.egg-info/PKG-INFO
network_changer.egg-info/SOURCES.txt
network_changer.egg-info/dependency_links.txt
network_changer.egg-info/entry_points.txt
network_changer.egg-info/requires.txt
network_changer.egg-info/top_level.txt
network_changer/platforms/__init__.py
network_changer/platforms/airport.py
network_changer/platforms/base.py
network_changer/platforms/dbus.py
network_changer/platforms/iw.py
network_changer/platforms/iwlib.py