Metadata-Version: 2.1
Name: network-changer
Version: 0.1.0
Summary: Utility for changing to an unsecured network
Home-page: https://github.com/delfick/network_changer
Author: Stephen Moore
Author-email: github@delfick.com
License: MIT
Requires-Python: >= 3.7
Provides-Extra: tests
Provides-Extra: sdbus
License-File: LICENSE
